bpl_api/Client.py
bpl_api/Connection.py
bpl_api/Constants.py
bpl_api/Exceptions.py
bpl_api/__init__.py
bpl_api/api/Accounts.py
bpl_api/api/Blocks.py
bpl_api/api/Delegates.py
bpl_api/api/Loader.py
bpl_api/api/Multisignatures.py
bpl_api/api/Peers.py
bpl_api/api/Resource.py
bpl_api/api/Signatures.py
bpl_api/api/Transactions.py
bpl_api/api/__init__.py
bpl_api-0.1.0.dist-info/METADATA
bpl_api-0.1.0.dist-info/RECORD
bpl_api-0.1.0.dist-info/WHEEL
bpl_api-0.1.0.dist-info/top_level.txt
