Metadata-Version: 2.1
Name: bpl-api
Version: 0.1.0
Summary: An API for the Blockpool Blockchain.
Home-page: https://github.com/DuneRoot/bpl-api
Author: Alistair O'Brien
Author-email: alistair.o'brien@ellesmere.com
License: UNKNOWN
Platform: UNKNOWN
Requires-Dist: requests
